odoo_test_helper/__init__.py
odoo_test_helper/fake_model_loader.py
odoo_test_helper-2.0.4.dist-info/METADATA
odoo_test_helper-2.0.4.dist-info/WHEEL
odoo_test_helper-2.0.4.dist-info/top_level.txt
odoo_test_helper-2.0.4.dist-info/RECORD
