Metadata-Version: 2.1
Name: odoo-test-helper
Version: 2.0.4
Summary: Odoo Test Helper
Home-page: http://github.com/OCA/odoo-test-helper
Author: Odoo Community Association (OCA)
Author-email: support@odoo-community.org
License: LGPLv3+
Classifier: Development Status :: 5 - Production/Stable
Classifier: Intended Audience :: Developers
Classifier: License :: OSI Approved :: GNU Lesser General Public License v3 or later (LGPLv3+)
Classifier: Programming Language :: Python :: 2
Classifier: Programming Language :: Python :: 2.7
Classifier: Programming Language :: Python :: 3
Classifier: Programming Language :: Python :: 3.5
Classifier: Programming Language :: Python :: 3.6
Classifier: Programming Language :: Python :: 3.7
Classifier: Programming Language :: Python :: 3.8
Classifier: Framework :: Odoo
